ner_annotator/__init__.py
ner_annotator/__main__.py
ner_annotator/annotator.py
ner_annotator/config.py
ner_annotator/model.py
ner_annotator/resources/__init__.py
ner_annotator/resources/icons/__init__.py
ner_annotator/resources/icons/categorize.png
ner_annotator/resources/icons/next.png
ner_annotator/resources/icons/previous.png
ner_annotator/resources/icons/save.png
ner_annotator/resources/icons/skip.png
ner_annotator/resources/style/__init__.py
ner_annotator/resources/style/style.qss
ner_annotator-0.1.1.dist-info/LICENSE
ner_annotator-0.1.1.dist-info/METADATA
ner_annotator-0.1.1.dist-info/WHEEL
ner_annotator-0.1.1.dist-info/entry_points.txt
ner_annotator-0.1.1.dist-info/top_level.txt
ner_annotator-0.1.1.dist-info/RECORD
