Metadata-Version: 2.1
Name: ner-annotator
Version: 0.1.1
Summary: GUI useful to manually annotate text for Named Entity Recognition purposes
Home-page: https://github.com/Wadaboa/ner-annotator
Author: Alessio Falai
Author-email: falai.alessio@gmail.com
License: UNKNOWN
Keywords: ner annotator entity recognition spacy
Platform: UNKNOWN
Classifier: Programming Language :: Python :: 3
Classifier: License :: OSI Approved :: MIT License
Classifier: Operating System :: OS Independent
Requires-Python: >=3.6
Requires-Dist: pyqt5 (==5.12)
Provides-Extra: spacy
Requires-Dist: spacy (==2.2.4) ; extra == 'spacy'
